{
  "latestVersion": "1.3.39",
  "stableVersion": "1.3.39",
  "activeVersion": "1.3.39",
  "previousStableVersion": "1.3.38",
  "latestVersionCode": 52,
  "stableVersionCode": 52,
  "activeVersionCode": 52,
  "apkDownloadUrl": "https://github.com/stralner2711-a11y/xpresshub/releases/download/v1.3.39/xpressintra.apk",
  "stableApkDownloadUrl": "https://github.com/stralner2711-a11y/xpresshub/releases/download/v1.3.39/xpressintra.apk",
  "previousStableApkDownloadUrl": "https://github.com/stralner2711-a11y/xpresshub/releases/download/v1.3.38/xpressintra.apk",
  "releasePageUrl": "https://github.com/stralner2711-a11y/xpresshub/releases/tag/v1.3.39",
  "stableReleasePageUrl": "https://github.com/stralner2711-a11y/xpresshub/releases/tag/v1.3.39",
  "downloadPageUrl": "https://stralner2711-a11y.github.io/xpresshub/download.html",
  "changelog": [
    "build 52: opdateringssystemet bruger nu flere officielle GitHub-kilder, hvis GitHub Pages er langsom",
    "Creator kan se hvilken version-kilde appen sidst hentede fra i opdateringspanelet",
    "Udgivelsesknappen stopper nu, hvis GitHub release, version.json eller APK-link ikke kan verificeres"
  ],
  "forceUpdate": true,
  "rollbackReason": "",
  "defectiveVersions": [],
  "updatedAt": "2026-06-23"
}
