{
  "latestVersion": "1.3.7",
  "stableVersion": "1.3.7",
  "activeVersion": "1.3.7",
  "previousStableVersion": "1.3.6",
  "latestVersionCode": 20,
  "stableVersionCode": 20,
  "activeVersionCode": 20,
  "apkDownloadUrl": "https://github.com/stralner2711-a11y/xpresshub/releases/download/v1.3.7/xpressintra.apk",
  "releasePageUrl": "https://github.com/stralner2711-a11y/xpresshub/releases/tag/v1.3.7",
  "downloadPageUrl": "https://stralner2711-a11y.github.io/xpresshub/download.html",
  "changelog": [
    "Medarbejdere oprettes nu med standardkoden xpress i stedet for invitationslink",
    "Første login tvinger brugeren til at lave sin egen personlige adgangskode",
    "Chef/creator får en kort besked, der kan sendes til kollegaen uden teknisk link",
    "Supabase SQL-pakken er opdateret med standardkode-onboarding og password reset-status"
  ],
  "forceUpdate": true,
  "rollbackReason": "",
  "defectiveVersions": [],
  "updatedAt": "2026-06-04"
}
